jupyterlab_scicap_verdant/__init__.py
jupyterlab_scicap_verdant/_version.py
jupyterlab_scicap_verdant/handlers.py
jupyterlab_scicap_verdant-0.1.1.data/data/etc/jupyter/jupyter_server_config.d/verdant.json
jupyterlab_scicap_verdant-0.1.1.data/data/share/jupyter/labextensions/jupyterlab-scicap-verdant/build_log.json
jupyterlab_scicap_verdant-0.1.1.data/data/share/jupyter/labextensions/jupyterlab-scicap-verdant/install.json
jupyterlab_scicap_verdant-0.1.1.data/data/share/jupyter/labextensions/jupyterlab-scicap-verdant/package.json
jupyterlab_scicap_verdant-0.1.1.data/data/share/jupyter/labextensions/jupyterlab-scicap-verdant/static/4f3a0b123bd6444bc928ed88841f256aeaa42a8a46e055b315137ff42ccab76d.svg
jupyterlab_scicap_verdant-0.1.1.data/data/share/jupyter/labextensions/jupyterlab-scicap-verdant/static/lib_index_js.65be01ef872fd3f14a5b.js
jupyterlab_scicap_verdant-0.1.1.data/data/share/jupyter/labextensions/jupyterlab-scicap-verdant/static/lib_index_js.65be01ef872fd3f14a5b.js.map
jupyterlab_scicap_verdant-0.1.1.data/data/share/jupyter/labextensions/jupyterlab-scicap-verdant/static/remoteEntry.85269238288de7222138.js
jupyterlab_scicap_verdant-0.1.1.data/data/share/jupyter/labextensions/jupyterlab-scicap-verdant/static/remoteEntry.85269238288de7222138.js.map
jupyterlab_scicap_verdant-0.1.1.data/data/share/jupyter/labextensions/jupyterlab-scicap-verdant/static/style.js
jupyterlab_scicap_verdant-0.1.1.data/data/share/jupyter/labextensions/jupyterlab-scicap-verdant/static/vendors-node_modules_diff_dist_diff_js.9e2712625aca761d2af5.js
jupyterlab_scicap_verdant-0.1.1.data/data/share/jupyter/labextensions/jupyterlab-scicap-verdant/static/vendors-node_modules_diff_dist_diff_js.9e2712625aca761d2af5.js.map
jupyterlab_scicap_verdant-0.1.1.data/data/share/jupyter/labextensions/jupyterlab-scicap-verdant/static/vendors-node_modules_prop-types_index_js.195d377cf8d9b294a7de.js
jupyterlab_scicap_verdant-0.1.1.dist-info/METADATA
jupyterlab_scicap_verdant-0.1.1.dist-info/WHEEL
jupyterlab_scicap_verdant-0.1.1.dist-info/licenses/LICENSE
jupyterlab_scicap_verdant-0.1.1.dist-info/RECORD
